pyspiget/__init__.py
pyspiget/spiget.py
pyspiget-1.0.0.dist-info/LICENSE
pyspiget-1.0.0.dist-info/METADATA
pyspiget-1.0.0.dist-info/WHEEL
pyspiget-1.0.0.dist-info/top_level.txt
pyspiget-1.0.0.dist-info/RECORD
