Metadata-Version: 2.1
Name: pyspiget
Version: 1.0.0
Summary: Simple Python wrapper for the Spiget API
Home-page: https://github.com/Mark7888/pyspiget
Author: Mark7888
Author-email: l.mark7888@gmail.com
Project-URL: Documentation, https://github.com/Mark7888/pyspiget/blob/master/README.md
Project-URL: Bug Reports, https://github.com/Mark7888/pyspiget/issues
Project-URL: Source Code, https://github.com/Mark7888/pyspiget
Keywords: spiget,spigot,minecraft,api,wrapper,plugins,resources
Classifier: Development Status :: 5 - Production/Stable
Classifier: Intended Audience :: Developers
Classifier: Topic :: Internet :: WWW/HTTP
Classifier: Topic :: Software Development :: Libraries :: Python Modules
Classifier: Topic :: Games/Entertainment
Classifier: Programming Language :: Python :: 3
Classifier: Programming Language :: Python :: 3.1
Classifier: Programming Language :: Python :: 3.2
Classifier: Programming Language :: Python :: 3.3
Classifier: Programming Language :: Python :: 3.4
Classifier: Programming Language :: Python :: 3.5
Classifier: Programming Language :: Python :: 3.6
Classifier: Programming Language :: Python :: 3.7
Classifier: Programming Language :: Python :: 3.8
Classifier: Programming Language :: Python :: 3.9
Classifier: Programming Language :: Python :: 3.10
Classifier: Programming Language :: Python :: 3.11
Classifier: Programming Language :: Python :: 3.12
Classifier: Programming Language :: Python :: 3.13
Classifier: Programming Language :: Python :: 3 :: Only
Classifier: License :: OSI Approved :: MIT License
Classifier: Operating System :: OS Independent
Requires-Python: >=3
License-File: LICENSE
Requires-Dist: requests>=2.31.0
